vibe_finder/__init__.py
vibe_finder/matcher.py
vibe_finder/py.typed
vibe_finder-1.5.2.dist-info/licenses/LICENSE
vibe_finder-1.5.2.dist-info/METADATA
vibe_finder-1.5.2.dist-info/WHEEL
vibe_finder-1.5.2.dist-info/top_level.txt
vibe_finder-1.5.2.dist-info/RECORD
