Metadata-Version: 2.4
Name: vibe-finder
Version: 1.5.2
Summary: Gap-tolerant fuzzy phrase matching for OCR documents and AI/LLM-generated text search. Find phrases even when text is altered, prettified, or contains OCR errors - without agentic multi-iteration approaches.
License: MIT
Project-URL: Homepage, https://github.com/LifeAITools/vibe-finder
Project-URL: Issues, https://github.com/LifeAITools/vibe-finder/issues
Keywords: fuzzy,search,matching,text,nlp,jaro-winkler,phrase,finder,vibe,ocr,llm,ai,document-search
Classifier: Development Status :: 5 - Production/Stable
Classifier: Intended Audience :: Developers
Classifier: License :: OSI Approved :: MIT License
Classifier: Operating System :: OS Independent
Classifier: Programming Language :: Python :: 3
Classifier: Programming Language :: Python :: 3.8
Classifier: Programming Language :: Python :: 3.9
Classifier: Programming Language :: Python :: 3.10
Classifier: Programming Language :: Python :: 3.11
Classifier: Programming Language :: Python :: 3.12
Classifier: Topic :: Text Processing :: Indexing
Classifier: Topic :: Text Processing :: Linguistic
Requires-Python: >=3.8
License-File: LICENSE
Dynamic: license-file
